scut/__init__.py
scut/databases/__init__.py
scut/databases/mongodb.py
scut/databases/redis.py
scut/websites/__init__.py
scut/websites/http.py
scut-0.0.1.dist-info/LICENSE
scut-0.0.1.dist-info/METADATA
scut-0.0.1.dist-info/WHEEL
scut-0.0.1.dist-info/top_level.txt
scut-0.0.1.dist-info/RECORD
