Metadata-Version: 2.1
Name: scut
Version: 0.0.1
Summary: UNKNOWN
Home-page: UNKNOWN
Author: UNKNOWN
Author-email: UNKNOWN
License: UNKNOWN
Platform: UNKNOWN
Requires-Dist: bunt (>=0.0.1)
Requires-Dist: docker (==4.1.0)
Requires-Dist: pymongo (==3.9.0)
Requires-Dist: requests (==2.21.0)
Requires-Dist: redis (==3.3.11)
